{"detail_done_cnt": 0, "rule1_cnt": 0, "times": "2016-08-16 01:52:44", "detail_cnt": 0, "rule0_cnt": 0, "list_done_cnt": 0, "list_cnt": 0}
{"detail_done_cnt": 0, "rule1_cnt": 0, "times": "2016-08-16 01:52:49", "detail_cnt": 0, "rule0_cnt": 0, "list_done_cnt": 0, "list_cnt": 0}
{"detail_done_cnt": 0, "rule1_cnt": 0, "times": "2016-08-16 01:54:35", "detail_cnt": 0, "rule0_cnt": 0, "list_done_cnt": 0, "list_cnt": 0}
{"detail_done_cnt": 0, "rule1_cnt": 0, "times": "2016-08-16 02:02:03", "detail_cnt": 2044, "rule0_cnt": 0, "list_done_cnt": 31, "list_cnt": 621}
{"detail_done_cnt": 0, "rule1_cnt": 0, "times": "2016-08-16 02:02:05", "detail_cnt": 2212, "rule0_cnt": 0, "list_done_cnt": 31, "list_cnt": 645}
