{"detail_done_cnt": 0, "rule1_cnt": 0, "times": "2016-08-03 18:56:07", "detail_cnt": 0, "rule0_cnt": 0, "list_done_cnt": 11, "list_cnt": 48}
{"detail_done_cnt": 0, "rule1_cnt": 0, "times": "2016-08-03 18:56:09", "detail_cnt": 0, "rule0_cnt": 0, "list_done_cnt": 11, "list_cnt": 48}
{"detail_done_cnt": 0, "rule1_cnt": 0, "times": "2016-08-03 18:56:39", "detail_cnt": 0, "rule0_cnt": 0, "list_done_cnt": 21, "list_cnt": 183}
{"detail_done_cnt": 0, "rule1_cnt": 0, "times": "2016-08-03 18:57:11", "detail_cnt": 0, "rule0_cnt": 0, "list_done_cnt": 41, "list_cnt": 230}
{"detail_done_cnt": 0, "rule1_cnt": 0, "times": "2016-08-03 18:57:42", "detail_cnt": 0, "rule0_cnt": 0, "list_done_cnt": 51, "list_cnt": 238}
{"detail_done_cnt": 0, "rule1_cnt": 0, "times": "2016-08-03 18:58:13", "detail_cnt": 0, "rule0_cnt": 0, "list_done_cnt": 61, "list_cnt": 238}
